taco/__init__.py
taco/aws_wrappers/__init__.py
taco/aws_wrappers/auto_scaler_wrapper/__init__.py
taco/aws_wrappers/auto_scaler_wrapper/auto_scaler_wrapper.py
taco/aws_wrappers/auto_scaler_wrapper/consts.py
taco/aws_wrappers/auto_scaler_wrapper/exceptions.py
taco/aws_wrappers/dynamodb_wrapper/__init__.py
taco/aws_wrappers/dynamodb_wrapper/condition.py
taco/aws_wrappers/dynamodb_wrapper/consts.py
taco/aws_wrappers/dynamodb_wrapper/dynamodb_wrapper.py
taco/aws_wrappers/dynamodb_wrapper/exceptions.py
taco/aws_wrappers/dynamodb_wrapper/table_creation_config.py
taco/aws_wrappers/s3_wrapper/__init__.py
taco/aws_wrappers/s3_wrapper/consts.py
taco/aws_wrappers/s3_wrapper/exceptions.py
taco/aws_wrappers/s3_wrapper/s3_wrapper.py
taco/aws_wrappers/sqs_wrapper/__init__.py
taco/aws_wrappers/sqs_wrapper/configs.py
taco/aws_wrappers/sqs_wrapper/consts.py
taco/aws_wrappers/sqs_wrapper/exceptions.py
taco/aws_wrappers/sqs_wrapper/sqs_message_wrapper.py
taco/aws_wrappers/sqs_wrapper/sqs_wrapper.py
taco/aws_wrappers/ssm_wrapper/__init__.py
taco/aws_wrappers/ssm_wrapper/consts.py
taco/aws_wrappers/ssm_wrapper/exceptions.py
taco/aws_wrappers/ssm_wrapper/ssm_wrapper.py
taco/boto3/__init__.py
taco/boto3/boto3_helpers.py
taco/boto3/boto_config.py
taco/common/__init__.py
taco/common/exceptions.py
taco/common/logger_based_object.py
taco/logger/__init__.py
taco/logger/consts.py
taco/logger/logger.py
taco/message_duplication_handler/__init__.py
taco/message_duplication_handler/consts.py
taco/message_duplication_handler/message_duplication_handler.py
taco/message_scheduler/__init__.py
taco/message_scheduler/consts.py
taco/message_scheduler/exceptions.py
taco/message_scheduler/message_scheduler.py
taco/mutex/__init__.py
taco/mutex/consts.py
taco/mutex/exceptions.py
taco/mutex/mutex.py
taco/mutex/mutex_table_creation_config.py
taco/ref_count_manager/__init__.py
taco/ref_count_manager/consts.py
taco/ref_count_manager/exceptions.py
taco/ref_count_manager/ref_count_manager.py
IntsightsTaco-0.0.1.dist-info/LICENSE
IntsightsTaco-0.0.1.dist-info/METADATA
IntsightsTaco-0.0.1.dist-info/WHEEL
IntsightsTaco-0.0.1.dist-info/top_level.txt
IntsightsTaco-0.0.1.dist-info/RECORD
