Metadata-Version: 2.1
Name: IntsightsTaco
Version: 0.0.1
Summary: Intsights open-source library for some AWS resources and high level management objects for distributed backend systems
Home-page: https://github.com/Intsights/taco
Author: Intsights
Author-email: Yair.Kuznitsov@intsights.com
License: UNKNOWN
Project-URL: Bug Reports, https://github.com/Intsights/taco/issues
Project-URL: Source, https://github.com/Intsights/taco/
Platform: UNKNOWN
Classifier: Programming Language :: Python :: 3.6
Classifier: Programming Language :: Python :: 3.7
Classifier: License :: OSI Approved :: Apache Software License
Classifier: Operating System :: OS Independent
Requires-Python: >=3.6
Requires-Dist: boto3 (>=1.9.224)
Requires-Dist: botocore (>=1.12.224)
Requires-Dist: awscli (>=1.16.234)
